[
  {
    "id": "r1",
    "name": "Tanta",
    "address": "Miraflores",
    "cuisine": "Peruvian",
    "website": "https://www.tanta.com",
    "description": "Good!\r\n"
  },
  {
    "id": "r2",
    "name": "Test 2",
    "address": "San Isidro",
    "cuisine": "Peruvian",
    "website": "https://www.tanta.com",
    "description": "Awesome!"
  },
  {
    "name": "Punto Azul",
    "address": "Miraflores",
    "cuisine": "Peruvian",
    "website": "https://www.puntoazul.com",
    "description": "Good",
    "id": "cb3f5e6f-0316-4a72-b619-69741b44bb70"
  },
  {
    "name": "Auna",
    "address": "Surco",
    "cuisine": "Peruvian",
    "website": "https://www.auna.com",
    "description": "Nice",
    "id": "e2b5755a-3913-405d-87df-048826a64b72"
  }
]
